runcx/__init__.py
runcx/runc.py
runcx-0.1.dist-info/METADATA
runcx-0.1.dist-info/WHEEL
runcx-0.1.dist-info/entry_points.txt
runcx-0.1.dist-info/top_level.txt
runcx-0.1.dist-info/RECORD
